{"frameNumber":138,"timestamp":"Nov 22 2018","glyphData":[{"type":"shape","shape":{"type":"circle","radius":2.52},"index":10204,"position":{"x":73.56,"y":0},"color":"#47B347","alpha":1},{"type":"shape","shape":{"type":"circle","radius":3.09},"index":2050,"position":{"x":-99.57,"y":-4.89},"color":"#B34747","alpha":1},{"type":"shape","shape":{"type":"circle","radius":2.52},"index":2909,"position":{"x":-81.9,"y":40.84},"color":"#B34747","alpha":1},{"type":"shape","shape":{"type":"circle","radius":2.52},"index":2066,"position":{"x":-45.44,"y":-178.02},"color":"#B34747","alpha":1},{"type":"shape","shape":{"type":"circle","radius":2.52},"index":2069,"position":{"x":153.27,"y":-97.48},"color":"#B34747","alpha":1},{"type":"shape","shape":{"type":"circle","radius":2.52},"index":10209,"position":{"x":122.29,"y":-4.95},"color":"#47B347","alpha":1},{"type":"shape","shape":{"type":"circle","radius":1.95},"index":3521,"position":{"x":217.18,"y":8.25},"color":"#662828","alpha":1},{"type":"shape","shape":{"type":"circle","radius":5.23},"index":2739,"position":{"x":-125.43,"y":-75.02},"color":"#B34747","alpha":1},{"type":"shape","shape":{"type":"circle","radius":2.52},"index":2267,"position":{"x":94.87,"y":30.27},"color":"#B34747","alpha":1},{"type":"composite","index":10194,"position":{"x":0,"y":0},"rotation":0.59209,"children":[{"type":"shape","shape":{"type":"circleSector","innerRadius":26.24548,"outerRadius":192.82068,"startAngle":-0.09163,"endAngle":0.09163},"index":10195,"position":{"x":0,"y":0},"color":"#07A9AA","alpha":0.1},{"type":"shape","shape":{"type":"circle","radius":2.52},"index":10196,"position":{"x":107.4,"y":-3.03},"color":"#47B347","alpha":1},{"type":"shape","shape":{"type":"circle","radius":1.78},"index":10197,"position":{"x":138.61,"y":-2.08},"color":"#662828","alpha":1},{"type":"shape","shape":{"type":"circle","radius":2.52},"index":10198,"position":{"x":176.81,"y":-5.11},"color":"#47B347","alpha":1},{"type":"shape","shape":{"type":"circle","radius":2.52},"index":10199,"position":{"x":149.89,"y":-1.84},"color":"#47B347","alpha":1},{"type":"shape","shape":{"type":"circle","radius":2.52},"index":10200,"position":{"x":135.57,"y":6.49},"color":"#47B347","alpha":1},{"type":"shape","shape":{"type":"circle","radius":2.52},"index":10201,"position":{"x":177.99,"y":9.92},"color":"#47B347","alpha":1},{"type":"shape","shape":{"type":"circle","radius":2.52},"index":10202,"position":{"x":166.77,"y":-4.48},"color":"#47B347","alpha":1},{"type":"shape","shape":{"type":"circle","radius":2.52},"index":10203,"position":{"x":122.86,"y":5.16},"color":"#47B347","alpha":1},{"type":"shape","shape":{"type":"circle","radius":2.52},"index":10204,"position":{"x":73.56,"y":0},"color":"#47B347","alpha":1},{"type":"shape","shape":{"type":"circle","radius":2.52},"index":10205,"position":{"x":163.62,"y":6.05},"color":"#47B347","alpha":1},{"type":"shape","shape":{"type":"circle","radius":2.52},"index":10206,"position":{"x":157.15,"y":-8.42},"color":"#47B347","alpha":0},{"type":"shape","shape":{"type":"circle","radius":2.52},"index":10207,"position":{"x":151.32,"y":8.13},"color":"#47B347","alpha":1},{"type":"shape","shape":{"type":"circle","radius":2.52},"index":10208,"position":{"x":90.31,"y":-2.16},"color":"#4747B3","alpha":1},{"type":"shape","shape":{"type":"circle","radius":2.52},"index":10209,"position":{"x":122.29,"y":-4.95},"color":"#47B347","alpha":1},{"type":"shape","shape":{"type":"circle","radius":2.52},"index":10210,"position":{"x":185.21,"y":-1.67},"color":"#47B347","alpha":1},{"type":"label","index":10211,"position":{"x":148.63,"y":0},"color":"#808080","alpha":1,"text":"efm32pg_stk3402a","fontSize":10,"rotation":0,"anchor":"BOTTOM_LEFT"}]},{"type":"shape","shape":{"type":"circle","radius":2.52},"index":2068,"position":{"x":142.16,"y":-112.47},"color":"#47B347","alpha":1},{"type":"shape","shape":{"type":"circle","radius":2.52},"index":2369,"position":{"x":-65.45,"y":17.26},"color":"#B34747","alpha":0},{"type":"shape","shape":{"type":"circle","radius":2.52},"index":10196,"position":{"x":107.4,"y":-3.03},"color":"#47B347","alpha":1},{"type":"shape","shape":{"type":"circle","radius":3.78},"index":2566,"position":{"x":106.04,"y":-42.5},"color":"#B34747","alpha":1},{"type":"shape","shape":{"type":"circle","radius":1.78},"index":2065,"position":{"x":-27.02,"y":-175.65},"color":"#662828","alpha":1},{"type":"shape","shape":{"type":"circle","radius":2.52},"index":2067,"position":{"x":-168.52,"y":73.62},"color":"#47B347","alpha":1},{"type":"shape","shape":{"type":"circle","radius":2.52},"index":10200,"position":{"x":135.57,"y":6.49},"color":"#47B347","alpha":1},{"type":"shape","shape":{"type":"circle","radius":5.61},"index":2041,"position":{"x":99.47,"y":-115.71},"color":"#B34747","alpha":1},{"type":"shape","shape":{"type":"circle","radius":1.78},"index":10197,"position":{"x":138.61,"y":-2.08},"color":"#662828","alpha":1},{"type":"shape","shape":{"type":"circleSector","innerRadius":26.24548,"outerRadius":192.82068,"startAngle":-0.09163,"endAngle":0.09163},"index":10195,"position":{"x":0,"y":0},"color":"#07A9AA","alpha":0.1},{"type":"shape","shape":{"type":"circle","radius":6.13},"index":2371,"position":{"x":85.61,"y":-55.99},"color":"#B34747","alpha":1},{"type":"shape","shape":{"type":"circle","radius":3.34},"index":2040,"position":{"x":146.3,"y":-36.78},"color":"#B34747","alpha":1},{"type":"shape","shape":{"type":"circle","radius":2.52},"index":10203,"position":{"x":122.86,"y":5.16},"color":"#47B347","alpha":1},{"type":"shape","shape":{"type":"circle","radius":2.52},"index":10208,"position":{"x":90.31,"y":-2.16},"color":"#4747B3","alpha":1},{"type":"label","index":10211,"position":{"x":148.63,"y":0},"color":"#808080","alpha":1,"text":"efm32pg_stk3402a","fontSize":10,"rotation":0,"anchor":"BOTTOM_LEFT"}]}