{"frameNumber":463,"timestamp":"Aug 29 2025","glyphData":[{"type":"shape","shape":{"type":"circle","radius":2.52},"index":13025,"position":{"x":135.3,"y":-4.37},"color":"#47B347","alpha":1},{"type":"shape","shape":{"type":"circle","radius":2.52},"index":13022,"position":{"x":147.67,"y":11.93},"color":"#47B347","alpha":1},{"type":"composite","index":11346,"position":{"x":0,"y":0},"rotation":3.0938,"children":[{"type":"shape","shape":{"type":"circleSector","innerRadius":7.52313,"outerRadius":151.63963,"startAngle":-0.10642,"endAngle":0.10642},"index":11347,"position":{"x":0,"y":0},"color":"#F31060","alpha":0.1},{"type":"shape","shape":{"type":"circle","radius":2.52},"index":11348,"position":{"x":144.01,"y":-1.83},"color":"#47B347","alpha":1},{"type":"shape","shape":{"type":"circle","radius":1.78},"index":11349,"position":{"x":115.92,"y":6.02},"color":"#662828","alpha":1},{"type":"shape","shape":{"type":"circle","radius":2.52},"index":11350,"position":{"x":127.07,"y":-4},"color":"#47B347","alpha":1},{"type":"shape","shape":{"type":"circle","radius":2.52},"index":11351,"position":{"x":102.76,"y":-3.03},"color":"#47B347","alpha":1},{"type":"shape","shape":{"type":"circle","radius":2.52},"index":11352,"position":{"x":116.73,"y":-6.25},"color":"#47B347","alpha":1},{"type":"shape","shape":{"type":"circle","radius":2.52},"index":11353,"position":{"x":68.92,"y":0},"color":"#47B347","alpha":1},{"type":"shape","shape":{"type":"circle","radius":2.52},"index":11354,"position":{"x":85.66,"y":-2.16},"color":"#47B347","alpha":1},{"type":"shape","shape":{"type":"circle","radius":2.52},"index":11355,"position":{"x":129.26,"y":7.73},"color":"#4747B3","alpha":1},{"type":"label","index":11356,"position":{"x":154.02,"y":0},"color":"#808080","alpha":1,"text":"blackpill_h523ce","fontSize":10,"rotation":0,"anchor":"RIGHT"}]},{"type":"shape","shape":{"type":"circle","radius":2.52},"index":11351,"position":{"x":102.76,"y":-3.03},"color":"#47B347","alpha":1},{"type":"shape","shape":{"type":"circle","radius":2.52},"index":7190,"position":{"x":244.49,"y":4.57},"color":"#47B347","alpha":1},{"type":"shape","shape":{"type":"circle","radius":2.52},"index":8603,"position":{"x":187.15,"y":7.63},"color":"#47B347","alpha":1},{"type":"shape","shape":{"type":"circle","radius":2.52},"index":11355,"position":{"x":129.26,"y":7.73},"color":"#4747B3","alpha":1},{"type":"shape","shape":{"type":"circle","radius":2.52},"index":11348,"position":{"x":144.01,"y":-1.83},"color":"#47B347","alpha":1},{"type":"shape","shape":{"type":"circle","radius":9.92},"index":4278,"position":{"x":255.41,"y":-2.33},"color":"#B34747","alpha":1},{"type":"shape","shape":{"type":"circle","radius":2.52},"index":13031,"position":{"x":93.07,"y":-3.03},"color":"#47B347","alpha":1},{"type":"shape","shape":{"type":"circle","radius":2.52},"index":7215,"position":{"x":209.22,"y":-5.2},"color":"#47B347","alpha":1},{"type":"shape","shape":{"type":"circle","radius":2.52},"index":8599,"position":{"x":188.71,"y":21.79},"color":"#47B347","alpha":1},{"type":"shape","shape":{"type":"circle","radius":2.52},"index":11354,"position":{"x":85.66,"y":-2.16},"color":"#47B347","alpha":1},{"type":"shape","shape":{"type":"circle","radius":2.52},"index":13024,"position":{"x":123.82,"y":-11.95},"color":"#47B347","alpha":1},{"type":"label","index":9470,"position":{"x":94.67,"y":0},"color":"#808080","alpha":1,"text":"panb611evb","fontSize":10,"rotation":0,"anchor":"TOP_LEFT"},{"type":"shape","shape":{"type":"circle","radius":2.52},"index":11352,"position":{"x":116.73,"y":-6.25},"color":"#47B347","alpha":1},{"type":"shape","shape":{"type":"circle","radius":2.52},"index":13029,"position":{"x":59.23,"y":0},"color":"#47B347","alpha":1},{"type":"label","index":13034,"position":{"x":158.15,"y":0},"color":"#808080","alpha":1,"text":"esp32h2_devkitm","fontSize":10,"rotation":0,"anchor":"TOP_LEFT"},{"type":"label","index":11356,"position":{"x":154.02,"y":0},"color":"#808080","alpha":1,"text":"blackpill_h523ce","fontSize":10,"rotation":0,"anchor":"RIGHT"},{"type":"shape","shape":{"type":"circleSector","innerRadius":7.52313,"outerRadius":151.63963,"startAngle":-0.10642,"endAngle":0.10642},"index":11347,"position":{"x":0,"y":0},"color":"#F31060","alpha":0.1},{"type":"label","index":7196,"position":{"x":254.53,"y":0},"color":"#808080","alpha":1,"text":"ek_ra6m4","fontSize":10,"rotation":0,"anchor":"BOTTOM_LEFT"},{"type":"shape","shape":{"type":"circle","radius":2.52},"index":13030,"position":{"x":75.98,"y":-2.16},"color":"#47B347","alpha":1},{"type":"shape","shape":{"type":"circle","radius":2.52},"index":8582,"position":{"x":179.8,"y":-17.03},"color":"#47B347","alpha":1},{"type":"composite","index":13020,"position":{"x":0,"y":0},"rotation":5.75511,"children":[{"type":"shape","shape":{"type":"circleSector","innerRadius":39.90467,"outerRadius":156.40411,"startAngle":-0.15938,"endAngle":0.15938},"index":13021,"position":{"x":0,"y":0},"color":"#961986","alpha":0.1},{"type":"shape","shape":{"type":"circle","radius":2.52},"index":13022,"position":{"x":147.67,"y":11.93},"color":"#47B347","alpha":1},{"type":"shape","shape":{"type":"circle","radius":2.52},"index":13023,"position":{"x":118.61,"y":-3.99},"color":"#47B347","alpha":1},{"type":"shape","shape":{"type":"circle","radius":2.52},"index":13024,"position":{"x":123.82,"y":-11.95},"color":"#47B347","alpha":1},{"type":"shape","shape":{"type":"circle","radius":2.52},"index":13025,"position":{"x":135.3,"y":-4.37},"color":"#47B347","alpha":1},{"type":"shape","shape":{"type":"circle","radius":1.78},"index":13026,"position":{"x":133.09,"y":4.45},"color":"#662828","alpha":1},{"type":"shape","shape":{"type":"circle","radius":2.52},"index":13027,"position":{"x":106.84,"y":6.44},"color":"#47B347","alpha":1},{"type":"shape","shape":{"type":"circle","radius":2.52},"index":13028,"position":{"x":122.17,"y":9.33},"color":"#47B347","alpha":1},{"type":"shape","shape":{"type":"circle","radius":2.52},"index":13029,"position":{"x":59.23,"y":0},"color":"#47B347","alpha":1},{"type":"shape","shape":{"type":"circle","radius":2.52},"index":13030,"position":{"x":75.98,"y":-2.16},"color":"#47B347","alpha":1},{"type":"shape","shape":{"type":"circle","radius":2.52},"index":13031,"position":{"x":93.07,"y":-3.03},"color":"#47B347","alpha":1},{"type":"shape","shape":{"type":"circle","radius":2.52},"index":13032,"position":{"x":108.15,"y":-9.05},"color":"#4747B3","alpha":1},{"type":"shape","shape":{"type":"circle","radius":2.52},"index":13033,"position":{"x":141.18,"y":-15},"color":"#47B347","alpha":1},{"type":"label","index":13034,"position":{"x":158.15,"y":0},"color":"#808080","alpha":1,"text":"esp32h2_devkitm","fontSize":10,"rotation":0,"anchor":"TOP_LEFT"}]},{"type":"shape","shape":{"type":"circle","radius":2.52},"index":13027,"position":{"x":106.84,"y":6.44},"color":"#47B347","alpha":1},{"type":"shape","shape":{"type":"circleSector","innerRadius":39.90467,"outerRadius":156.40411,"startAngle":-0.15938,"endAngle":0.15938},"index":13021,"position":{"x":0,"y":0},"color":"#961986","alpha":0.1},{"type":"shape","shape":{"type":"circle","radius":2.52},"index":11353,"position":{"x":68.92,"y":0},"color":"#47B347","alpha":1},{"type":"shape","shape":{"type":"circle","radius":2.52},"index":13032,"position":{"x":108.15,"y":-9.05},"color":"#4747B3","alpha":1},{"type":"shape","shape":{"type":"circle","radius":2.52},"index":8581,"position":{"x":187.36,"y":-9.59},"color":"#47B347","alpha":1},{"type":"label","index":8611,"position":{"x":199.97,"y":0},"color":"#808080","alpha":1,"text":"nrf9280pdk","fontSize":10,"rotation":0,"anchor":"TOP_LEFT"},{"type":"shape","shape":{"type":"circle","radius":1.78},"index":11349,"position":{"x":115.92,"y":6.02},"color":"#662828","alpha":1},{"type":"shape","shape":{"type":"circle","radius":2.52},"index":9469,"position":{"x":78.18,"y":32.5},"color":"#47B347","alpha":1},{"type":"shape","shape":{"type":"circle","radius":2.52},"index":13023,"position":{"x":118.61,"y":-3.99},"color":"#47B347","alpha":1},{"type":"shape","shape":{"type":"circle","radius":2.52},"index":9461,"position":{"x":37.19,"y":6.63},"color":"#47B347","alpha":0},{"type":"shape","shape":{"type":"circle","radius":2.52},"index":13033,"position":{"x":141.18,"y":-15},"color":"#47B347","alpha":1},{"type":"shape","shape":{"type":"circle","radius":2.52},"index":13028,"position":{"x":122.17,"y":9.33},"color":"#47B347","alpha":1},{"type":"shape","shape":{"type":"circle","radius":1.78},"index":13026,"position":{"x":133.09,"y":4.45},"color":"#662828","alpha":1},{"type":"shape","shape":{"type":"circle","radius":2.52},"index":11350,"position":{"x":127.07,"y":-4},"color":"#47B347","alpha":1}]}