{"frameNumber":124,"timestamp":"Aug 8 2018","glyphData":[{"type":"shape","shape":{"type":"circle","radius":3.48},"index":12598,"position":{"x":97.21,"y":-2.94},"color":"#B34747","alpha":1},{"type":"shape","shape":{"type":"circle","radius":5.29},"index":12587,"position":{"x":80.76,"y":51.53},"color":"#B34747","alpha":1},{"type":"shape","shape":{"type":"circle","radius":5.64},"index":2808,"position":{"x":-0.22,"y":-64.23},"color":"#B34747","alpha":1},{"type":"shape","shape":{"type":"circle","radius":3.52},"index":12580,"position":{"x":87.36,"y":32.05},"color":"#B34747","alpha":1},{"type":"shape","shape":{"type":"circle","radius":9.76},"index":12597,"position":{"x":105.1,"y":28.23},"color":"#B34747","alpha":1}]}